{
  "intents": [
    {
      "intent": "ChapterIntent",
      "slots": [
        {
          "name": "book",
          "type": "LIST_OF_BOOKS"
        },
        {
          "name": "chapter",
          "type": "AMAZON.NUMBER"
        }
      ]
    },
    {
      "intent": "VerseIntent",
      "slots": [
        {
          "name": "book",
          "type": "LIST_OF_BOOKS"
        },
        {
          "name": "chapter",
          "type": "AMAZON.NUMBER"
        },
        {
          "name": "verse",
          "type": "AMAZON.NUMBER"
        }
      ]
    },
    {
      "intent": "VerseRangeIntent",
      "slots": [
        {
          "name": "book",
          "type": "LIST_OF_BOOKS"
        },
        {
          "name": "chapter",
          "type": "AMAZON.NUMBER"
        },
        {
          "name": "start_verse",
          "type": "AMAZON.NUMBER"
        },
        {
          "name": "end_verse",
          "type": "AMAZON.NUMBER"
        }
      ]
    },
    {
      "intent": "VerseExtraIntent",
      "slots": [
        {
          "name": "extra_option",
          "type": "VERSE_EXTRA_OPTION"
        }
      ]
    },
    {
      "intent": "CommentaryIntent",
      "slots": [
        {
          "name": "book",
          "type": "LIST_OF_BOOKS"
        },
        {
          "name": "chapter",
          "type": "AMAZON.NUMBER"
        },
        {
          "name": "verse",
          "type": "AMAZON.NUMBER"
        }
      ]
    },
    {
      "intent": "CommentaryRangeIntent",
      "slots": [
        {
          "name": "book",
          "type": "LIST_OF_BOOKS"
        },
        {
          "name": "chapter",
          "type": "AMAZON.NUMBER"
        },
        {
          "name": "start_verse",
          "type": "AMAZON.NUMBER"
        },
        {
          "name": "end_verse",
          "type": "AMAZON.NUMBER"
        }
      ]
    },
    {
      "intent": "CommentarySelectionIntent",
      "slots": [
        {
          "name": "commentary_number",
          "type": "AMAZON.NUMBER"
        }
      ]
    },
    {
      "intent": "AMAZON.CancelIntent"
    },
    {
      "intent": "AMAZON.StopIntent"
    },
    {
      "intent": "AMAZON.HelpIntent"
    }
  ]
}
